MANIFEST.in
README.rst
setup.py
django_kittenstorage.egg-info/PKG-INFO
django_kittenstorage.egg-info/SOURCES.txt
django_kittenstorage.egg-info/dependency_links.txt
django_kittenstorage.egg-info/top_level.txt
kittenstorage/__init__.py
kittenstorage/settings.py
kittenstorage/storages/ColorKitten.py
kittenstorage/storages/GreyKitten.py
kittenstorage/storages/__init__.py