Metadata-Version: 1.0
Name: django-kittenstorage
Version: 1.0.0
Summary: Django Storage Engine which returns images of kittens if files could not be found.
Home-page: https://github.com/originell/django-kittenstorage
Author: Luis Nell
Author-email: cooperate@originell.org
License: UNKNOWN
Platform: any
Classifier: Development Status :: 5 - Production/Stable
Classifier: Environment :: Web Environment
Classifier: Framework :: Django
Classifier: Intended Audience :: Developers
Classifier: License :: OSI Approved :: BSD License
Classifier: Operating System :: OS Independent
Classifier: Programming Language :: Python
Classifier: Topic :: Internet :: WWW/HTTP :: Dynamic Content
Classifier: Topic :: Multimedia :: Graphics
